{
  "reports": [
    {
      "slug": "honduras-presidential-election",
      "eventId": 74717,
      "title": "Honduras Presidential Election",
      "label": "normal",
      "score": 2.696864111498258,
      "updatedAt": "2025-12-13T05:19:53.638073+00:00",
      "lookbackSeconds": 86400,
      "tradeCount": 287,
      "lastTradeTimestamp": 1765600744,
      "topSignals": [
        "min-size trades share=25% over 287 trades",
        "wallet concentration top1=4% trades (8% notional), top3=11%"
      ],
      "outcomes": [
        {
          "label": "Will Jorge Nelson \u00c1vila Guti\u00e9rrez win the 2025 Honduras presidential election? (No)",
          "score": 31.0,
          "labelText": "normal"
        },
        {
          "label": "Will Mario Rivera Callejas win the 2025 Honduras presidential election? (Yes)",
          "score": 25.0,
          "labelText": "normal"
        },
        {
          "label": "Will Rixi Ramona Moncada Godoy win the 2025 Honduras presidential election? (Yes)",
          "score": 6.0,
          "labelText": "normal"
        },
        {
          "label": "Will Salvador Nasralla win the 2025 Honduras presidential election? (No)",
          "score": 5.741379310344827,
          "labelText": "normal"
        },
        {
          "label": "Will Jorge Nelson \u00c1vila Guti\u00e9rrez win the 2025 Honduras presidential election? (Yes)",
          "score": 5.624999999999999,
          "labelText": "normal"
        },
        {
          "label": "Will Nasry Juan Asfura Zablah win the 2025 Honduras presidential election? (No)",
          "score": 4.071428571428572,
          "labelText": "normal"
        },
        {
          "label": "Will Nasry Juan Asfura Zablah win the 2025 Honduras presidential election? (Yes)",
          "score": 3.8608695652173917,
          "labelText": "normal"
        },
        {
          "label": "Will Rixi Ramona Moncada Godoy win the 2025 Honduras presidential election? (No)",
          "score": 3.6428571428571423,
          "labelText": "normal"
        },
        {
          "label": "Will Salvador Nasralla win the 2025 Honduras presidential election? (Yes)",
          "score": 2.0377358490566038,
          "labelText": "normal"
        }
      ],
      "refreshMode": "scheduled"
    }
  ],
  "generatedAt": "2025-12-13T05:19:53.641754+00:00"
}