{
  "reports": [
    {
      "slug": "honduras-presidential-election",
      "eventId": 74717,
      "title": "Honduras Presidential Election",
      "label": "normal",
      "score": 2.6235,
      "updatedAt": "2025-12-04T10:24:04.475693+00:00",
      "lookbackSeconds": 86400,
      "tradeCount": 1000,
      "lastTradeTimestamp": 1764843801,
      "topSignals": [
        "wallet concentration top1=10% trades (25% notional), top3=22%",
        "min-size trades share=15% over 1000 trades"
      ],
      "outcomes": [
        {
          "label": "Will Jorge Nelson \u00c1vila Guti\u00e9rrez win the 2025 Honduras presidential election? (No)",
          "score": 25.0,
          "labelText": "normal"
        },
        {
          "label": "Will Mario Rivera Callejas win the 2025 Honduras presidential election? (Yes)",
          "score": 25.0,
          "labelText": "normal"
        },
        {
          "label": "Will Rixi Ramona Moncada Godoy win the 2025 Honduras presidential election? (No)",
          "score": 24.3135593220339,
          "labelText": "normal"
        },
        {
          "label": "Will Nasry Juan Asfura Zablah win the 2025 Honduras presidential election? (No)",
          "score": 4.844594594594595,
          "labelText": "normal"
        },
        {
          "label": "Will Salvador Nasralla win the 2025 Honduras presidential election? (No)",
          "score": 4.5,
          "labelText": "normal"
        },
        {
          "label": "Will Rixi Ramona Moncada Godoy win the 2025 Honduras presidential election? (Yes)",
          "score": 3.5833333333333335,
          "labelText": "normal"
        },
        {
          "label": "Will Nasry Juan Asfura Zablah win the 2025 Honduras presidential election? (Yes)",
          "score": 2.8704545454545456,
          "labelText": "normal"
        },
        {
          "label": "Will Salvador Nasralla win the 2025 Honduras presidential election? (Yes)",
          "score": 1.7492836676217765,
          "labelText": "normal"
        }
      ],
      "refreshMode": "scheduled"
    }
  ],
  "generatedAt": "2025-12-04T10:24:04.480834+00:00"
}