{
  "reports": [
    {
      "slug": "honduras-presidential-election",
      "eventId": 74717,
      "title": "Honduras Presidential Election",
      "label": "watch",
      "score": 46.7325,
      "updatedAt": "2025-12-10T14:49:49.261733+00:00",
      "lookbackSeconds": 86400,
      "tradeCount": 1000,
      "lastTradeTimestamp": 1765378136,
      "topSignals": [
        "min-size trades share=80% over 1000 trades",
        "ping-pong wallets share=71% of trades",
        "round-trip wallets share=72% of trades"
      ],
      "outcomes": [
        {
          "label": "Will Rixi Ramona Moncada Godoy win the 2025 Honduras presidential election? (No)",
          "score": 68.78561643835616,
          "labelText": "suspicious"
        },
        {
          "label": "Will Rixi Ramona Moncada Godoy win the 2025 Honduras presidential election? (Yes)",
          "score": 28.36057692307692,
          "labelText": "normal"
        },
        {
          "label": "Will Mario Rivera Callejas win the 2025 Honduras presidential election? (Yes)",
          "score": 25.0,
          "labelText": "normal"
        },
        {
          "label": "Will Jorge Nelson \u00c1vila Guti\u00e9rrez win the 2025 Honduras presidential election? (Yes)",
          "score": 25.0,
          "labelText": "normal"
        },
        {
          "label": "Will Nasry Juan Asfura Zablah win the 2025 Honduras presidential election? (Yes)",
          "score": 4.857142857142857,
          "labelText": "normal"
        },
        {
          "label": "Will Nasry Juan Asfura Zablah win the 2025 Honduras presidential election? (No)",
          "score": 4.666666666666667,
          "labelText": "normal"
        },
        {
          "label": "Will Salvador Nasralla win the 2025 Honduras presidential election? (Yes)",
          "score": 3.8625,
          "labelText": "normal"
        },
        {
          "label": "Will Salvador Nasralla win the 2025 Honduras presidential election? (No)",
          "score": 2.9999999999999996,
          "labelText": "normal"
        }
      ],
      "refreshMode": "scheduled"
    }
  ],
  "generatedAt": "2025-12-10T14:49:49.264928+00:00"
}